{
    "last_updated": "2026-01-29T02:48:15.706999+00:00",
    "last_successful_update": "2026-01-29T02:48:15.707006+00:00",
    "gms_score": 34,
    "sector_scores": {
        "STOCKS": 40,
        "CRYPTO": 40,
        "FOREX": 55,
        "COMMODITIES": 55
    },
    "market_data": {
        "CRYPTO_SENTIMENT": {
            "price": 26,
            "change_percent": 0.0,
            "trend": "BEARISH",
            "sparkline": [
                21,
                20,
                28,
                29,
                25,
                26,
                44,
                42,
                28,
                27,
                25,
                29,
                27,
                26,
                48,
                61,
                49,
                50,
                49,
                44,
                32,
                24,
                20,
                24,
                25,
                25,
                20,
                29,
                29,
                26
            ]
        },
        "YIELD_SPREAD": {
            "price": 0.58,
            "change_percent": 0.0,
            "trend": "NORMAL",
            "sparkline": [
                0.5,
                0.54,
                0.53,
                0.53,
                0.46,
                0.46,
                0.5,
                0.44,
                0.49,
                0.51,
                0.51,
                0.54,
                0.53,
                0.55,
                0.53,
                0.57,
                0.56,
                0.52,
                0.51,
                0.48,
                0.49,
                0.57,
                0.57,
                0.6,
                0.56,
                0.55,
                0.54,
                0.55,
                0.57,
                0.58
            ]
        },
        "HY_SPREAD": {
            "price": 2.71,
            "prev_price": 2.69,
            "daily_chg": 0.74,
            "change_percent": 0.74,
            "trend": "CALM",
            "sparkline": [
                2.99,
                2.95,
                2.9,
                2.88,
                2.83,
                2.84,
                2.84,
                2.86,
                2.87,
                2.84,
                2.81,
                2.81,
                2.83,
                2.81,
                2.79,
                2.79,
                2.76,
                2.74,
                2.74,
                2.75,
                2.76,
                2.71,
                2.65,
                2.65,
                2.73,
                2.69,
                2.64,
                2.68,
                2.69,
                2.71
            ]
        },
        "NFCI": {
            "price": -0.6,
            "change_percent": 0.0,
            "trend": "CALM",
            "sparkline": [
                -0.52,
                -0.52,
                -0.51,
                -0.51,
                -0.52,
                -0.52,
                -0.53,
                -0.54,
                -0.55,
                -0.56,
                -0.58,
                -0.59,
                -0.6
            ]
        },
        "NET_LIQUIDITY": {
            "price": 5714.22,
            "prev_price": 5714.07,
            "daily_chg": 0.0,
            "change_percent": 0.02,
            "trend": "EXPANSION",
            "sparkline": [
                5712.06,
                5720.72,
                5722.24,
                5717.88,
                5739.31,
                5739.31,
                5723.77,
                5733.56,
                5731.51,
                5697.32,
                5697.32,
                5797.65,
                5796.83,
                5800.73,
                5772.87,
                5774.37,
                5774.17,
                5774.05,
                5774.18,
                5799.3,
                5800.52,
                5801.3,
                5801.3,
                5799.02,
                5711.98,
                5713.26,
                5714.39,
                5713.83,
                5714.07,
                5714.22
            ]
        },
        "BREAKEVEN_INFLATION": {
            "price": 2.36,
            "change_percent": 0.0,
            "trend": "STABLE",
            "sparkline": [
                2.24,
                2.24,
                2.23,
                2.24,
                2.24,
                2.24,
                2.23,
                2.22,
                2.24,
                2.25,
                2.25,
                2.25,
                2.26,
                2.27,
                2.27,
                2.27,
                2.28,
                2.29,
                2.3,
                2.29,
                2.29,
                2.33,
                2.33,
                2.33,
                2.34,
                2.31,
                2.32,
                2.32,
                2.34,
                2.36
            ]
        },
        "VIX": {
            "price": 16.35,
            "prev_price": 16.35,
            "daily_chg": 0.0,
            "change_percent": 4.54,
            "trend": "DOWN",
            "sparkline": [
                13.6,
                14.2,
                14.33,
                14.95,
                14.51,
                14.9,
                14.75,
                15.38,
                15.45,
                14.49,
                15.12,
                15.98,
                16.75,
                15.84,
                15.86,
                20.09,
                16.9,
                15.64,
                16.09,
                16.15,
                16.35,
                16.35
            ]
        },
        "YIELD_SPREAD_10Y2Y": {
            "price": 0.7,
            "change_percent": 0.0,
            "trend": "NEUTRAL",
            "sparkline": [
                0.66,
                0.68,
                0.73,
                0.7,
                0.68,
                0.68,
                0.68,
                0.67,
                0.69,
                0.71,
                0.71,
                0.72,
                0.71,
                0.71,
                0.68,
                0.7,
                0.64,
                0.65,
                0.65,
                0.64,
                0.61,
                0.65,
                0.65,
                0.7,
                0.66,
                0.65,
                0.64,
                0.66,
                0.71,
                0.7
            ]
        },
        "US_10Y_YIELD": {
            "price": 4.24,
            "change_percent": 0.0,
            "trend": "STABLE",
            "sparkline": [
                4.16,
                4.12,
                4.16,
                4.17,
                4.18,
                4.15,
                4.15,
                4.14,
                4.12,
                4.14,
                4.18,
                4.18,
                4.19,
                4.17,
                4.18,
                4.15,
                4.19,
                4.18,
                4.19,
                4.18,
                4.15,
                4.17,
                4.24,
                4.24,
                4.3,
                4.26,
                4.26,
                4.24,
                4.22,
                4.24
            ]
        },
        "REAL_INTEREST_RATE": {
            "price": 1.9,
            "change_percent": 0.0,
            "trend": "STABLE",
            "sparkline": [
                1.92,
                1.88,
                1.92,
                1.94,
                1.94,
                1.91,
                1.91,
                1.91,
                1.9,
                1.9,
                1.93,
                1.93,
                1.94,
                1.91,
                1.91,
                1.88,
                1.92,
                1.9,
                1.9,
                1.88,
                1.86,
                1.88,
                1.91,
                1.91,
                1.97,
                1.92,
                1.95,
                1.92,
                1.9,
                1.9
            ]
        },
        "SPY": {
            "price": 695.42,
            "prev_price": 695.49,
            "daily_chg": -0.01,
            "change_percent": 0.93,
            "trend": "DOWN",
            "sparkline": [
                690.31,
                687.85,
                687.01,
                681.92,
                683.17,
                687.72,
                691.81,
                689.58,
                689.51,
                694.07,
                695.16,
                693.77,
                690.36,
                692.24,
                691.66,
                677.58,
                685.4,
                688.98,
                689.23,
                692.73,
                695.49,
                695.42
            ]
        },
        "TNX": {
            "price": 4.25,
            "prev_price": 4.22,
            "daily_chg": 0.66,
            "change_percent": 0.05,
            "trend": "UP",
            "sparkline": [
                4.14,
                4.12,
                4.13,
                4.16,
                4.19,
                4.16,
                4.18,
                4.14,
                4.18,
                4.17,
                4.19,
                4.17,
                4.14,
                4.16,
                4.23,
                4.3,
                4.25,
                4.25,
                4.24,
                4.21,
                4.22,
                4.25
            ]
        },
        "QQQ": {
            "price": 633.22,
            "prev_price": 631.13,
            "daily_chg": 0.33,
            "change_percent": 2.01,
            "trend": "UP",
            "sparkline": [
                623.89,
                620.87,
                619.43,
                614.31,
                613.12,
                617.99,
                623.42,
                624.02,
                620.47,
                626.65,
                627.17,
                626.24,
                619.55,
                621.78,
                621.26,
                608.06,
                616.28,
                620.76,
                622.72,
                625.46,
                631.13,
                633.22
            ]
        },
        "IWM": {
            "price": 263.3,
            "prev_price": 264.73,
            "daily_chg": -0.54,
            "change_percent": -2.41,
            "trend": "DOWN",
            "sparkline": [
                251.42,
                249.88,
                248.03,
                246.16,
                248.78,
                252.73,
                256.08,
                255.48,
                258.27,
                260.23,
                261.5,
                261.35,
                263.19,
                265.51,
                265.76,
                262.58,
                267.79,
                269.79,
                264.81,
                263.98,
                264.73,
                263.3
            ]
        },
        "RSP": {
            "price": 198.26,
            "prev_price": 198.93,
            "daily_chg": -0.34,
            "change_percent": -0.7,
            "trend": "DOWN",
            "sparkline": [
                193.84,
                193.52,
                193.21,
                191.56,
                192.86,
                194.65,
                197.0,
                194.79,
                196.46,
                197.6,
                197.78,
                197.78,
                198.68,
                199.56,
                199.05,
                196.08,
                199.4,
                199.66,
                198.77,
                199.24,
                198.93,
                198.26
            ]
        },
        "HYG": {
            "price": 81.04,
            "prev_price": 81.17,
            "daily_chg": -0.16,
            "change_percent": -0.17,
            "trend": "DOWN",
            "sparkline": [
                80.6,
                80.63,
                80.71,
                80.63,
                80.67,
                80.88,
                80.9,
                80.88,
                80.94,
                81.0,
                81.04,
                81.04,
                81.04,
                81.04,
                81.09,
                80.88,
                81.12,
                81.18,
                81.14,
                81.18,
                81.17,
                81.04
            ]
        },
        "NIFTY": {
            "price": 25342.75,
            "prev_price": 25175.4,
            "daily_chg": 0.66,
            "change_percent": 0.74,
            "trend": "UP",
            "sparkline": [
                26042.3,
                25942.1,
                25938.85,
                26129.6,
                26146.55,
                26328.55,
                26250.3,
                26178.7,
                26140.75,
                25876.85,
                25683.3,
                25790.25,
                25732.3,
                25665.6,
                25694.35,
                25585.5,
                25232.5,
                25157.5,
                25289.9,
                25048.65,
                25175.4,
                25342.75
            ]
        },
        "BTC": {
            "price": 88014.01,
            "prev_price": 89102.57,
            "daily_chg": -1.22,
            "change_percent": -1.23,
            "trend": "DOWN",
            "sparkline": [
                91308.05,
                91027.12,
                90513.1,
                90386.65,
                90827.46,
                91192.99,
                95321.78,
                96929.33,
                95551.19,
                95525.12,
                95099.92,
                93634.43,
                92553.59,
                88310.91,
                89376.96,
                89462.45,
                89503.88,
                89110.73,
                86572.22,
                88267.14,
                89102.57,
                88014.01
            ]
        },
        "ETH": {
            "price": 2961.73,
            "prev_price": 3022.21,
            "daily_chg": -2.0,
            "change_percent": 0.44,
            "trend": "DOWN",
            "sparkline": [
                3166.84,
                3104.38,
                3083.05,
                3082.4,
                3118.89,
                3092.33,
                3322.1,
                3354.72,
                3317.1,
                3295.48,
                3308.86,
                3281.16,
                3186.62,
                2935.61,
                2978.9,
                2949.63,
                2953.26,
                2948.74,
                2815.9,
                2926.46,
                3022.21,
                2961.73
            ]
        },
        "SOL": {
            "price": 123.58,
            "prev_price": 127.05,
            "daily_chg": -2.74,
            "change_percent": -2.74,
            "trend": "DOWN",
            "sparkline": [
                136.31,
                138.29,
                135.76,
                135.73,
                139.49,
                139.14,
                145.36,
                146.75,
                142.33,
                144.86,
                143.73,
                138.0,
                133.34,
                125.71,
                129.38,
                128.29,
                127.36,
                127.05,
                118.77,
                124.14,
                127.05,
                123.58
            ]
        },
        "DXY": {
            "price": 96.2,
            "prev_price": 96.22,
            "daily_chg": -0.02,
            "change_percent": -2.19,
            "trend": "DOWN",
            "sparkline": [
                98.02,
                98.04,
                98.24,
                98.28,
                98.42,
                98.27,
                98.58,
                98.68,
                98.93,
                99.13,
                98.86,
                99.13,
                99.13,
                99.32,
                99.39,
                98.64,
                98.76,
                98.36,
                97.6,
                97.04,
                96.22,
                96.2
            ]
        },
        "USDJPY": {
            "price": 153.1,
            "prev_price": 152.45,
            "daily_chg": 0.43,
            "change_percent": -3.41,
            "trend": "UP",
            "sparkline": [
                156.01,
                156.41,
                156.73,
                156.99,
                156.63,
                156.68,
                156.73,
                156.88,
                158.15,
                157.99,
                159.18,
                158.4,
                158.6,
                157.54,
                158.18,
                158.16,
                158.46,
                158.5,
                155.17,
                154.34,
                152.45,
                153.1
            ]
        },
        "EURUSD": {
            "price": 1.2,
            "prev_price": 1.2,
            "daily_chg": -0.35,
            "change_percent": 1.88,
            "trend": "DOWN",
            "sparkline": [
                1.18,
                1.17,
                1.18,
                1.17,
                1.17,
                1.17,
                1.17,
                1.17,
                1.16,
                1.17,
                1.16,
                1.16,
                1.16,
                1.16,
                1.16,
                1.17,
                1.17,
                1.18,
                1.19,
                1.19,
                1.2,
                1.2
            ]
        },
        "USDINR": {
            "price": 92.04,
            "prev_price": 91.53,
            "daily_chg": 0.55,
            "change_percent": 0.52,
            "trend": "UP",
            "sparkline": [
                89.9,
                89.77,
                89.96,
                90.01,
                90.23,
                90.17,
                89.86,
                89.91,
                90.24,
                90.13,
                90.27,
                90.18,
                90.36,
                90.7,
                90.9,
                91.12,
                91.54,
                91.56,
                91.5,
                91.71,
                91.53,
                92.04
            ]
        },
        "USDSAR": {
            "price": 3.75,
            "prev_price": 3.75,
            "daily_chg": 0.12,
            "change_percent": 0.13,
            "trend": "UP",
            "sparkline": [
                3.74,
                3.75,
                3.75,
                3.75,
                3.75,
                3.75,
                3.75,
                3.75,
                3.75,
                3.75,
                3.75,
                3.75,
                3.75,
                3.75,
                3.75,
                3.75,
                3.75,
                3.75,
                3.74,
                3.75,
                3.75,
                3.75
            ]
        },
        "GOLD": {
            "price": 5575.2,
            "prev_price": 5079.9,
            "daily_chg": 9.75,
            "change_percent": 13.58,
            "trend": "UP",
            "sparkline": [
                4529.1,
                4325.1,
                4370.1,
                4325.6,
                4314.4,
                4436.9,
                4482.2,
                4449.3,
                4449.7,
                4490.3,
                4604.3,
                4589.2,
                4626.3,
                4616.3,
                4588.4,
                4759.6,
                4831.8,
                4908.8,
                4976.2,
                5079.7,
                5079.9,
                5575.2
            ]
        },
        "OIL": {
            "price": 63.83,
            "prev_price": 62.39,
            "daily_chg": 2.31,
            "change_percent": 7.53,
            "trend": "UP",
            "sparkline": [
                56.74,
                58.08,
                57.95,
                57.42,
                57.32,
                58.32,
                57.13,
                55.99,
                57.76,
                59.12,
                59.5,
                61.15,
                62.02,
                59.19,
                59.44,
                60.34,
                60.62,
                59.36,
                61.07,
                60.63,
                62.39,
                63.83
            ]
        },
        "COPPER": {
            "price": 6.02,
            "prev_price": 5.83,
            "daily_chg": 3.35,
            "change_percent": 4.89,
            "trend": "UP",
            "sparkline": [
                5.77,
                5.49,
                5.73,
                5.63,
                5.64,
                5.92,
                6.01,
                5.81,
                5.75,
                5.86,
                5.99,
                5.97,
                6.01,
                5.95,
                5.79,
                5.77,
                5.73,
                5.74,
                5.91,
                5.98,
                5.83,
                6.02
            ]
        },
        "NATGAS": {
            "price": 3.76,
            "prev_price": 6.95,
            "daily_chg": -45.87,
            "change_percent": -25.39,
            "trend": "DOWN",
            "sparkline": [
                4.37,
                4.69,
                3.97,
                3.69,
                3.62,
                3.52,
                3.35,
                3.53,
                3.41,
                3.17,
                3.41,
                3.42,
                3.12,
                3.13,
                3.1,
                3.91,
                4.88,
                5.05,
                5.28,
                6.8,
                6.95,
                3.76
            ]
        },
        "MOVE": {
            "price": 57.43,
            "change_percent": 2.33,
            "trend": "NORMAL",
            "sparkline": [
                59.21,
                63.98,
                63.96,
                62.36,
                64.71,
                65.82,
                66.15,
                66.94,
                61.55,
                62.9,
                60.79,
                58.11,
                56.14,
                58.05,
                66.67,
                59.56,
                56.5,
                56.25,
                55.77,
                56.12,
                57.43
            ]
        },
        "BREADTH": {
            "price": -1.63,
            "change_percent": 0.0,
            "trend": "NARROW",
            "sparkline": [
                0.0,
                -0.04,
                -0.15,
                0.34,
                0.6,
                1.22,
                0.4,
                1.28,
                1.2,
                1.14,
                1.34,
                2.3,
                2.48,
                2.3,
                2.82,
                3.39,
                3.01,
                2.51,
                2.25,
                1.68,
                1.35
            ]
        },
        "SPY_MOMENTUM": {
            "price": 1.63,
            "change_percent": 0,
            "trend": "SKEWED",
            "sparkline": [
                0,
                0,
                0,
                0,
                0,
                0,
                0,
                0,
                0,
                0,
                0,
                0,
                0,
                0,
                0,
                0,
                0,
                0,
                0,
                0,
                0,
                0,
                0,
                0,
                0,
                0,
                0,
                0,
                0,
                0
            ]
        },
        "COPPER_GOLD": {
            "price": 1.08,
            "change_percent": 0,
            "trend": "RISK-OFF",
            "sparkline": [
                1.08,
                1.08,
                1.08,
                1.08,
                1.08,
                1.08,
                1.08,
                1.08,
                1.08,
                1.08,
                1.08,
                1.08,
                1.08,
                1.08,
                1.08,
                1.08,
                1.08,
                1.08,
                1.08,
                1.08,
                1.08,
                1.08,
                1.08,
                1.08,
                1.08,
                1.08,
                1.08,
                1.08,
                1.08,
                1.08
            ]
        }
    },
    "events": [
        {
            "code": "nfp",
            "name": "NON-FARM PAYROLLS",
            "date": "2026-02-06",
            "day": "FRI",
            "time": "08:30 EST",
            "impact": "high"
        },
        {
            "code": "cpi",
            "name": "CPI INFLATION DATA",
            "date": "2026-02-12",
            "day": "THU",
            "time": "08:30 EST",
            "impact": "high"
        },
        {
            "code": "fomc",
            "name": "FOMC RATE DECISION",
            "date": "2026-03-18",
            "day": "WED",
            "time": "14:00 EST",
            "impact": "critical"
        }
    ],
    "analysis": {
        "title": "Global Market Outlook",
        "content": "GMS Status: Defensive (Score 34). Stable DXY (Dollar strength/Liquidity) and contained VIX (Fear/Volatility) suggest broad panic is limited. Surging Gold/Oil and falling crypto reinforce inflation/geopolitical concerns, warranting a risk-off stance. Though defensive, a stable VIX could hint at short-term tactical opportunities despite underlying risks...",
        "reports": {
            "JP": "GMSステータス: 防御的 (スコア34)。DXY (ドル高/流動性) の安定とVIX (恐怖/変動性) の抑制は、広範なパニックが限定的であることを示唆。金と原油の急騰、仮想通貨の下落は、インフレ/地政学的懸念を裏付け、リスクオフ姿勢を正当化。防御的ではあるものの、VIXの安定は短期的な戦術的リスク資産機会を示唆する可能性あり。..",
            "EN": "GMS Status: Defensive (Score 34). Stable DXY (Dollar strength/Liquidity) and contained VIX (Fear/Volatility) suggest broad panic is limited. Surging Gold/Oil and falling crypto reinforce inflation/geopolitical concerns, warranting a risk-off stance. Though defensive, a stable VIX could hint at short-term tactical opportunities despite underlying risks...",
            "CN": "GMS状态：防御性（分数34）。DXY（美元走强/流动性）稳定和VIX（恐惧/波动性）受控表明广泛恐慌有限。黄金和石油飙升，加密货币下跌，强化了通胀/地缘政治担忧，需采取避险立场。尽管防御性，稳定的VIX可能预示短期战术性风险资产机会，尽管存在潜在风险。..",
            "ES": "Estado GMS: Defensivo (Puntuación 34). DXY (fortaleza del dólar/liquidez) estable y VIX (miedo/volatilidad) contenido sugieren pánico limitado. El aumento del oro y petróleo, con caída de cripto, refuerzan preocupaciones de inflación/geopolíticas, justificando una postura de riesgo-off. Aunque defensivo, un VIX estable podría ofrecer oportunidades tácticas a corto plazo pese a riesgos...",
            "HI": "जीएमएस स्थिति: रक्षात्मक (स्कोर 34)। स्थिर DXY (डॉलर मजबूती/तरलता) और नियंत्रित VIX (डर/अस्थिरता) व्यापक घबराहट को सीमित करते हैं। सोने और तेल में उछाल, और क्रिप्टो में गिरावट, मुद्रास्फीति/भू-राजनीतिक चिंताओं को बल देते हैं, जिससे जोखिम-मुक्त रुख बनता है। रक्षात्मक होते हुए भी, स्थिर VIX अल्पकालिक रणनीतिक जोखिम संपत्ति के अवसर दे सकता है।..",
            "ID": "Status GMS: Defensif (Skor 34). DXY (kekuatan Dolar/Likuiditas) stabil dan VIX (Ketakutan/Volatilitas) terkendali menunjukkan kepanikan luas terbatas. Emas dan Minyak melonjak, kripto jatuh, memperkuat kekhawatiran inflasi/geopolitik, sehingga perlu sikap risk-off. Meski defensif, VIX stabil bisa memberi peluang taktis jangka pendek meski ada risiko...",
            "AR": "حالة GMS: دفاعية (النقاط 34). استقرار مؤشر الدولار (DXY) (قوة الدولار/السيولة) واحتواء مؤشر VIX (الخوف/التقلب) يشيران إلى ذعر محدود. ارتفاع الذهب والنفط وهبوط العملات المشفرة يعززان مخاوف التضخم/الجيوسياسية، مما يتطلب موقفًا دفاعيًا. على الرغم من الموقف الدفاعي، قد يشير استقرار VIX إلى فرص تكتيكية قصيرة الأجل رغم المخاطر الكامنة..."
        }
    },
    "history_chart": [
        {
            "date": "2026-01-27T04:02:21Z",
            "score": 39
        },
        {
            "date": "2026-01-27T04:55:30Z",
            "score": 39
        },
        {
            "date": "2026-01-27T05:40:12Z",
            "score": 39
        },
        {
            "date": "2026-01-27T06:53:31Z",
            "score": 39
        },
        {
            "date": "2026-01-27T07:38:31Z",
            "score": 39
        },
        {
            "date": "2026-01-27T08:49:17Z",
            "score": 39
        },
        {
            "date": "2026-01-27T09:45:55Z",
            "score": 39
        },
        {
            "date": "2026-01-27T10:44:30Z",
            "score": 40
        },
        {
            "date": "2026-01-27T11:33:52Z",
            "score": 40
        },
        {
            "date": "2026-01-27T11:53:04Z",
            "score": 40
        },
        {
            "date": "2026-01-27T13:12:31Z",
            "score": 40
        },
        {
            "date": "2026-01-27T13:54:16Z",
            "score": 40
        },
        {
            "date": "2026-01-27T14:21:39Z",
            "score": 40
        },
        {
            "date": "2026-01-27T14:26:19Z",
            "score": 40
        },
        {
            "date": "2026-01-27T14:50:02Z",
            "score": 38
        },
        {
            "date": "2026-01-27T15:00:25Z",
            "score": 38
        },
        {
            "date": "2026-01-27T15:29:51Z",
            "score": 38
        },
        {
            "date": "2026-01-27T15:41:21Z",
            "score": 38
        },
        {
            "date": "2026-01-27T15:53:03Z",
            "score": 38
        },
        {
            "date": "2026-01-27T15:57:13Z",
            "score": 38
        },
        {
            "date": "2026-01-27T16:04:51Z",
            "score": 38
        },
        {
            "date": "2026-01-28T01:00:58Z",
            "score": 40
        },
        {
            "date": "2026-01-28T01:42:34Z",
            "score": 40
        },
        {
            "date": "2026-01-28T01:50:14Z",
            "score": 40
        },
        {
            "date": "2026-01-28T03:09:12Z",
            "score": 40
        },
        {
            "date": "2026-01-28T04:53:41Z",
            "score": 40
        },
        {
            "date": "2026-01-28T05:17:03Z",
            "score": 40
        },
        {
            "date": "2026-01-28T05:40:52Z",
            "score": 40
        },
        {
            "date": "2026-01-28T05:56:03Z",
            "score": 40
        },
        {
            "date": "2026-01-28T05:59:29Z",
            "score": 40
        },
        {
            "date": "2026-01-28T06:34:43Z",
            "score": 43
        },
        {
            "date": "2026-01-28T06:47:58Z",
            "score": 40
        },
        {
            "date": "2026-01-28T06:53:10Z",
            "score": 40
        },
        {
            "date": "2026-01-28T07:37:29Z",
            "score": 41
        },
        {
            "date": "2026-01-28T08:49:31Z",
            "score": 38
        },
        {
            "date": "2026-01-28T09:46:30Z",
            "score": 41
        },
        {
            "date": "2026-01-28T10:44:08Z",
            "score": 41
        },
        {
            "date": "2026-01-28T11:33:51Z",
            "score": 41
        },
        {
            "date": "2026-01-28T13:12:43Z",
            "score": 41
        },
        {
            "date": "2026-01-28T13:53:07Z",
            "score": 41
        },
        {
            "date": "2026-01-28T14:00:48Z",
            "score": 41
        },
        {
            "date": "2026-01-28T14:08:01Z",
            "score": 41
        },
        {
            "date": "2026-01-28T14:19:45Z",
            "score": 40
        },
        {
            "date": "2026-01-28T14:30:37Z",
            "score": 40
        },
        {
            "date": "2026-01-28T14:40:51Z",
            "score": 39
        },
        {
            "date": "2026-01-28T14:45:25Z",
            "score": 39
        },
        {
            "date": "2026-01-28T15:46:53Z",
            "score": 37
        },
        {
            "date": "2026-01-28T16:54:11Z",
            "score": 36
        },
        {
            "date": "2026-01-28T17:44:33Z",
            "score": 36
        },
        {
            "date": "2026-01-28T18:52:12Z",
            "score": 36
        },
        {
            "date": "2026-01-28T19:40:04Z",
            "score": 37
        },
        {
            "date": "2026-01-28T20:47:07Z",
            "score": 37
        },
        {
            "date": "2026-01-28T21:41:02Z",
            "score": 34
        },
        {
            "date": "2026-01-28T22:40:15Z",
            "score": 34
        },
        {
            "date": "2026-01-28T23:06:19Z",
            "score": 37
        },
        {
            "date": "2026-01-28T23:37:18Z",
            "score": 37
        },
        {
            "date": "2026-01-29T00:17:36Z",
            "score": 34
        },
        {
            "date": "2026-01-29T01:25:01Z",
            "score": 34
        },
        {
            "date": "2026-01-29T02:45:32Z",
            "score": 34
        },
        {
            "date": "2026-01-29T02:48:15Z",
            "score": 34
        }
    ],
    "intelligence": {
        "news": [
            {
                "title": "Tesla tops estimates for quarter, but wraps up first annual revenue drop on record",
                "link": "https://www.cnbc.com/2026/01/28/tesla-tsla-2025-q4-earnings.html",
                "isoDate": "2026-01-28T23:32:20+00:00Z"
            },
            {
                "title": "Meta’s Reality Labs posts $6.02 billion loss in fourth quarter",
                "link": "https://www.cnbc.com/2026/01/28/metas-reality-labs-posts-6point02-billion-loss-in-fourth-quarter.html",
                "isoDate": "2026-01-29T01:12:05+00:00Z"
            },
            {
                "title": "Gold and silver keep hitting record highs. But is the precious metals market 'broken'?",
                "link": "https://www.cnbc.com/2026/01/29/gold-and-silver-keep-hitting-record-high-but-the-market-may-be-broken.html",
                "isoDate": "2026-01-29T01:32:42+00:00Z"
            },
            {
                "title": "S&P 500 futures slip as gold prices surge, traders weigh tech giants' earnings: Live updates",
                "link": "https://www.cnbc.com/2026/01/28/stock-market-today-live-updates.html",
                "isoDate": "2026-01-29T00:34:35+00:00Z"
            },
            {
                "title": "Microsoft stock drops 7% on slowing cloud growth, light margin guidance",
                "link": "https://www.cnbc.com/2026/01/28/microsoft-msft-q2-earnings-report-2026.html",
                "isoDate": "2026-01-28T23:58:16+00:00Z"
            },
            {
                "title": "Investors will have to wait a bit longer for any rate cuts this year",
                "link": "https://www.cnbc.com/2026/01/28/investors-may-have-to-wait-a-bit-longer-for-any-rate-cuts-this-year.html",
                "isoDate": "2026-01-28T21:35:07+00:00Z"
            }
        ],
        "translations": {
            "JP": [
                "テスラ、四半期決算は予想を上回るも、記録的な年次売上高は初の下落",
                "MetaのReality Labs、第4四半期に60.2億ドルの損失を計上",
                "金と銀が記録的高値を更新し続ける。しかし、貴金属市場は「壊れている」のか？",
                "S&P500先物は下落、金価格は急騰、トレーダーは大手ハイテク企業の決算を注視：ライブアップデート",
                "マイクロソフト株、クラウド成長鈍化と利益率ガイダンスの低迷で7%下落",
                "投資家は年内の利下げをもう少し待つ必要がありそう"
            ],
            "CN": [
                "特斯拉季度业绩超预期，但全年营收录得首次下滑",
                "Meta的Reality Labs第四季度亏损60.2亿美元",
                "黄金和白银持续创纪录新高。但贵金属市场是否“失灵”？",
                "标普500指数期货下跌，因金价飙升，交易员权衡科技巨头财报：实时更新",
                "微软股价因云计算增长放缓、利润指引疲软下跌7%",
                "投资者今年降息将需再等待一段时间"
            ],
            "ES": [
                "Tesla supera las estimaciones trimestrales, pero registra la primera caída anual de ingresos récord",
                "Reality Labs de Meta registra una pérdida de 6.020 millones de dólares en el cuarto trimestre",
                "El oro y la plata siguen alcanzando máximos históricos. ¿Pero está el mercado de metales preciosos 'roto'?",
                "Los futuros del S&P 500 caen mientras los precios del oro se disparan, los operadores sopesan las ganancias de los gigantes tecnológicos: Actualizaciones en vivo",
                "Las acciones de Microsoft caen un 7% por la desaceleración del crecimiento en la nube y una guía de márgenes débil",
                "Los inversores tendrán que esperar un poco más para cualquier recorte de tasas este año"
            ],
            "HI": [
                "टेस्ला ने तिमाही के अनुमानों को पार किया, लेकिन रिकॉर्ड वार्षिक राजस्व में पहली गिरावट दर्ज की",
                "मेटा का रियलिटी लैब्स चौथी तिमाही में 6.02 अरब डॉलर का घाटा दर्ज करता है",
                "सोना और चांदी रिकॉर्ड ऊंचाई पर पहुंच रहे हैं। लेकिन क्या कीमती धातुओं का बाजार 'बिगड़' गया है?",
                "सोने की कीमतों में उछाल के साथ एसएंडपी 500 फ्यूचर्स फिसले, ट्रेडर्स टेक दिग्गजों की कमाई पर विचार कर रहे हैं: लाइव अपडेट",
                "क्लाउड ग्रोथ में सुस्ती, मार्जिन गाइडेंस हल्के रहने से माइक्रोसॉफ्ट के शेयर 7% गिरे",
                "निवेशकों को इस साल दर कटौती के लिए थोड़ा और इंतजार करना होगा"
            ],
            "ID": [
                "Tesla melampaui perkiraan kuartalan, namun catat penurunan pendapatan tahunan pertama yang rekor",
                "Reality Labs Meta membukukan kerugian $6,02 miliar di kuartal keempat",
                "Emas dan perak terus mencapai rekor tertinggi. Tapi apakah pasar logam mulia 'rusak'?",
                "Futures S&P 500 merosot karena harga emas melonjak, pedagang mempertimbangkan laba raksasa teknologi: Pembaruan langsung",
                "Saham Microsoft anjlok 7% karena pertumbuhan cloud yang melambat, panduan margin yang ringan",
                "Investor harus menunggu sedikit lebih lama untuk setiap penurunan suku bunga tahun ini"
            ],
            "AR": [
                "تسلا تتصدر التقديرات للربع، لكنها تختتم أول انخفاض سنوي في الإيرادات على الإطلاق",
                "تسجل Reality Labs التابعة لشركة Meta خسارة قدرها 6.02 مليار دولار في الربع الرابع",
                "يواصل الذهب والفضة تحقيق مستويات قياسية. لكن هل سوق المعادن الثمينة \"معطل\"؟",
                "عقود S&P 500 الآجلة تتراجع مع ارتفاع أسعار الذهب، والمتداولون يزنون أرباح عمالقة التكنولوجيا: تحديثات مباشرة",
                "أسهم مايكروسوفت تنخفض 7% بسبب تباطؤ نمو السحابة وتوجيهات هامش ضعيفة",
                "سيتعين على المستثمرين الانتظار لفترة أطول قليلاً لأي تخفيضات في أسعار الفائدة هذا العام"
            ]
        },
        "last_updated": "2026-01-29T02:48:15.706500+00:00Z"
    },
    "system_status": "OPERATIONAL"
}