{
    "last_updated": "2026-02-21T11:23:24.657306+00:00",
    "last_successful_update": "2026-02-21T11:23:24.657314+00:00",
    "gms_score": 54,
    "sector_scores": {
        "STOCKS": 56,
        "CRYPTO": 56,
        "FOREX": 41,
        "COMMODITIES": 53,
        "GLOBAL_INDICES": 50,
        "REAL_ESTATE": 50,
        "CREDIT": 50,
        "TRADE_LOGISTICS": 50,
        "THEMATIC": 50,
        "GLOBAL_FX": 50
    },
    "market_data": {
        "CRYPTO_SENTIMENT": {
            "price": 8,
            "daily_chg": 14.29,
            "change_percent": -20.0,
            "trend": "FEAR",
            "sparkline": [
                24,
                25,
                25,
                20,
                29,
                29,
                26,
                16,
                20,
                14,
                14,
                17,
                14,
                12,
                9,
                6,
                7,
                14,
                9,
                11,
                5,
                9,
                9,
                8,
                12,
                10,
                8,
                9,
                7,
                8
            ]
        },
        "YIELD_SPREAD": {
            "price": 0.39,
            "change_percent": 0.0,
            "trend": "NORMAL",
            "sparkline": [
                0.52,
                0.51,
                0.48,
                0.49,
                0.57,
                0.57,
                0.6,
                0.56,
                0.55,
                0.54,
                0.55,
                0.57,
                0.58,
                0.57,
                0.59,
                0.6,
                0.59,
                0.6,
                0.54,
                0.54,
                0.53,
                0.47,
                0.48,
                0.39,
                0.36,
                0.36,
                0.36,
                0.39,
                0.39,
                0.39
            ]
        },
        "HY_SPREAD": {
            "price": 2.88,
            "prev_price": 2.86,
            "daily_chg": 0.7,
            "change_percent": 0.7,
            "trend": "CALM",
            "sparkline": [
                2.74,
                2.75,
                2.76,
                2.71,
                2.65,
                2.65,
                2.73,
                2.69,
                2.64,
                2.68,
                2.69,
                2.71,
                2.72,
                2.77,
                2.8,
                2.88,
                2.81,
                2.85,
                2.86,
                2.97,
                2.87,
                2.84,
                2.86,
                2.84,
                2.92,
                2.95,
                2.94,
                2.94,
                2.86,
                2.88
            ]
        },
        "NFCI": {
            "price": -0.57,
            "change_percent": 0.0,
            "trend": "CALM",
            "sparkline": [
                -0.51,
                -0.52,
                -0.52,
                -0.53,
                -0.54,
                -0.55,
                -0.56,
                -0.56,
                -0.57,
                -0.57,
                -0.57,
                -0.57
            ]
        },
        "NET_LIQUIDITY": {
            "price": 5700.17,
            "prev_price": 5700.04,
            "daily_chg": 0.0,
            "change_percent": -0.11,
            "trend": "EXPANSION",
            "sparkline": [
                5774.05,
                5774.18,
                5799.3,
                5800.52,
                5801.3,
                5801.3,
                5799.02,
                5711.98,
                5713.26,
                5714.39,
                5713.83,
                5714.07,
                5663.42,
                5661.67,
                5654.9,
                5654.11,
                5662.74,
                5694.72,
                5695.39,
                5694.02,
                5695.83,
                5695.69,
                5706.03,
                5704.23,
                5706.7,
                5706.7,
                5706.64,
                5699.81,
                5700.04,
                5700.17
            ]
        },
        "BREAKEVEN_INFLATION": {
            "price": 2.28,
            "change_percent": 0.0,
            "trend": "STABLE",
            "sparkline": [
                2.29,
                2.3,
                2.29,
                2.29,
                2.33,
                2.33,
                2.33,
                2.34,
                2.31,
                2.32,
                2.32,
                2.34,
                2.36,
                2.35,
                2.36,
                2.35,
                2.36,
                2.35,
                2.32,
                2.34,
                2.35,
                2.32,
                2.32,
                2.29,
                2.27,
                2.27,
                2.26,
                2.29,
                2.29,
                2.28
            ]
        },
        "VIX": {
            "price": 19.09,
            "prev_price": 20.23,
            "daily_chg": -5.64,
            "change_percent": -7.33,
            "trend": "DOWN",
            "sparkline": [
                16.9,
                15.64,
                16.09,
                16.15,
                16.35,
                16.35,
                16.88,
                17.44,
                16.34,
                18.0,
                18.64,
                21.77,
                20.37,
                17.36,
                17.79,
                17.65,
                20.82,
                20.6,
                20.29,
                19.62,
                20.23,
                19.09
            ]
        },
        "YIELD_SPREAD_10Y2Y": {
            "price": 0.6,
            "change_percent": 0.0,
            "trend": "NEUTRAL",
            "sparkline": [
                0.65,
                0.65,
                0.64,
                0.61,
                0.65,
                0.65,
                0.7,
                0.66,
                0.65,
                0.64,
                0.66,
                0.71,
                0.7,
                0.71,
                0.74,
                0.72,
                0.71,
                0.72,
                0.74,
                0.72,
                0.74,
                0.71,
                0.66,
                0.62,
                0.64,
                0.64,
                0.62,
                0.62,
                0.61,
                0.6
            ]
        },
        "US_10Y_YIELD": {
            "price": 4.08,
            "change_percent": 0.0,
            "trend": "STABLE",
            "sparkline": [
                4.18,
                4.19,
                4.18,
                4.15,
                4.17,
                4.24,
                4.24,
                4.3,
                4.26,
                4.26,
                4.24,
                4.22,
                4.24,
                4.26,
                4.24,
                4.26,
                4.29,
                4.28,
                4.29,
                4.21,
                4.22,
                4.22,
                4.16,
                4.18,
                4.09,
                4.04,
                4.04,
                4.05,
                4.09,
                4.08
            ]
        },
        "REAL_INTEREST_RATE": {
            "price": 1.79,
            "change_percent": 0.0,
            "trend": "STABLE",
            "sparkline": [
                1.9,
                1.9,
                1.88,
                1.86,
                1.88,
                1.91,
                1.91,
                1.97,
                1.92,
                1.95,
                1.92,
                1.9,
                1.9,
                1.9,
                1.89,
                1.9,
                1.94,
                1.92,
                1.94,
                1.89,
                1.88,
                1.87,
                1.84,
                1.86,
                1.8,
                1.77,
                1.77,
                1.79,
                1.8,
                1.79
            ]
        },
        "SPY": {
            "price": 689.43,
            "prev_price": 684.48,
            "daily_chg": 0.72,
            "change_percent": 1.13,
            "trend": "UP",
            "sparkline": [
                685.4,
                688.98,
                689.23,
                692.73,
                695.49,
                695.42,
                694.04,
                691.97,
                695.41,
                689.53,
                686.19,
                677.62,
                690.62,
                693.95,
                692.12,
                691.96,
                681.27,
                681.75,
                682.85,
                686.29,
                684.48,
                689.43
            ]
        },
        "TNX": {
            "price": 4.09,
            "prev_price": 4.07,
            "daily_chg": 0.27,
            "change_percent": 0.74,
            "trend": "UP",
            "sparkline": [
                4.25,
                4.25,
                4.24,
                4.21,
                4.22,
                4.25,
                4.23,
                4.24,
                4.28,
                4.27,
                4.28,
                4.21,
                4.21,
                4.2,
                4.15,
                4.17,
                4.1,
                4.06,
                4.05,
                4.08,
                4.07,
                4.09
            ]
        },
        "QQQ": {
            "price": 608.81,
            "prev_price": 603.47,
            "daily_chg": 0.88,
            "change_percent": 1.14,
            "trend": "UP",
            "sparkline": [
                616.28,
                620.76,
                622.72,
                625.46,
                631.13,
                633.22,
                629.43,
                621.87,
                626.14,
                616.52,
                605.75,
                597.03,
                609.65,
                614.32,
                611.47,
                613.11,
                600.64,
                601.92,
                601.3,
                605.79,
                603.47,
                608.81
            ]
        },
        "IWM": {
            "price": 264.61,
            "prev_price": 264.6,
            "daily_chg": 0.0,
            "change_percent": 0.63,
            "trend": "UP",
            "sparkline": [
                267.79,
                269.79,
                264.81,
                263.98,
                264.73,
                263.3,
                263.37,
                259.65,
                262.18,
                262.78,
                260.52,
                255.83,
                265.02,
                266.88,
                266.16,
                264.95,
                259.54,
                262.96,
                263.04,
                263.99,
                264.6,
                264.61
            ]
        },
        "RSP": {
            "price": 204.09,
            "prev_price": 203.14,
            "daily_chg": 0.47,
            "change_percent": 0.6,
            "trend": "UP",
            "sparkline": [
                199.4,
                199.66,
                198.77,
                199.24,
                198.93,
                198.26,
                198.52,
                198.08,
                199.1,
                198.57,
                200.3,
                198.56,
                202.26,
                202.38,
                203.1,
                203.46,
                200.79,
                202.87,
                202.52,
                203.57,
                203.14,
                204.09
            ]
        },
        "HYG": {
            "price": 81.0,
            "prev_price": 80.94,
            "daily_chg": 0.07,
            "change_percent": 0.19,
            "trend": "UP",
            "sparkline": [
                80.72,
                80.78,
                80.74,
                80.78,
                80.77,
                80.64,
                80.63,
                80.72,
                80.77,
                80.72,
                80.62,
                80.53,
                80.81,
                80.92,
                80.84,
                80.83,
                80.79,
                80.85,
                80.81,
                80.91,
                80.94,
                81.0
            ]
        },
        "NIFTY": {
            "price": 25571.25,
            "prev_price": 25454.35,
            "daily_chg": 0.46,
            "change_percent": -0.43,
            "trend": "UP",
            "sparkline": [
                25157.5,
                25289.9,
                25048.65,
                25175.4,
                25342.75,
                25418.9,
                25320.65,
                25088.4,
                25727.55,
                25776.0,
                25642.8,
                25693.7,
                25867.3,
                25935.15,
                25953.85,
                25807.2,
                25471.1,
                25682.75,
                25725.4,
                25819.35,
                25454.35,
                25571.25
            ]
        },
        "BTC": {
            "price": 68240.76,
            "prev_price": 68005.42,
            "daily_chg": 0.35,
            "change_percent": 1.11,
            "trend": "UP",
            "sparkline": [
                78621.12,
                76974.45,
                78688.77,
                75633.55,
                73019.7,
                62702.1,
                70555.39,
                69281.97,
                70264.73,
                70120.78,
                68793.96,
                66991.97,
                66221.84,
                68857.84,
                69767.62,
                68788.19,
                68843.16,
                67494.22,
                66425.32,
                66957.52,
                68005.42,
                68240.76
            ]
        },
        "ETH": {
            "price": 1982.74,
            "prev_price": 1969.02,
            "daily_chg": 0.7,
            "change_percent": -0.47,
            "trend": "UP",
            "sparkline": [
                2445.09,
                2267.96,
                2344.36,
                2227.56,
                2143.5,
                1821.68,
                2063.39,
                2090.55,
                2088.76,
                2103.57,
                2019.5,
                1940.62,
                1946.94,
                2048.53,
                2086.01,
                1966.04,
                1997.92,
                1992.19,
                1953.97,
                1948.2,
                1969.02,
                1982.74
            ]
        },
        "SOL": {
            "price": 85.52,
            "prev_price": 84.64,
            "daily_chg": 1.04,
            "change_percent": 0.37,
            "trend": "UP",
            "sparkline": [
                105.44,
                100.85,
                104.47,
                97.56,
                92.03,
                78.19,
                87.46,
                87.64,
                87.04,
                86.7,
                82.92,
                79.25,
                78.35,
                84.32,
                88.16,
                86.01,
                86.43,
                85.2,
                81.57,
                82.39,
                84.64,
                85.52
            ]
        },
        "DXY": {
            "price": 97.8,
            "prev_price": 97.93,
            "daily_chg": -0.13,
            "change_percent": 0.95,
            "trend": "DOWN",
            "sparkline": [
                98.76,
                98.36,
                97.6,
                97.04,
                96.22,
                96.45,
                96.28,
                96.99,
                97.61,
                97.44,
                97.62,
                97.82,
                97.63,
                96.82,
                96.8,
                96.83,
                96.93,
                96.88,
                97.16,
                97.7,
                97.93,
                97.8
            ]
        },
        "USDJPY": {
            "price": 155.16,
            "prev_price": 154.69,
            "daily_chg": 0.3,
            "change_percent": 1.56,
            "trend": "UP",
            "sparkline": [
                158.46,
                158.5,
                155.17,
                154.34,
                152.45,
                153.1,
                153.16,
                155.2,
                155.44,
                155.8,
                156.92,
                156.78,
                157.24,
                156.13,
                154.48,
                153.27,
                152.82,
                152.78,
                153.61,
                153.15,
                154.69,
                155.16
            ]
        },
        "EURUSD": {
            "price": 1.18,
            "prev_price": 1.18,
            "daily_chg": -0.17,
            "change_percent": -0.83,
            "trend": "DOWN",
            "sparkline": [
                1.17,
                1.18,
                1.19,
                1.19,
                1.2,
                1.2,
                1.2,
                1.18,
                1.18,
                1.18,
                1.18,
                1.18,
                1.18,
                1.19,
                1.19,
                1.19,
                1.19,
                1.19,
                1.18,
                1.19,
                1.18,
                1.18
            ]
        },
        "USDINR": {
            "price": 91.04,
            "prev_price": 90.79,
            "daily_chg": 0.27,
            "change_percent": 0.52,
            "trend": "UP",
            "sparkline": [
                91.54,
                91.56,
                91.5,
                91.71,
                91.53,
                92.04,
                91.78,
                91.69,
                90.25,
                90.42,
                90.12,
                90.31,
                90.59,
                90.82,
                90.59,
                90.74,
                90.56,
                90.57,
                90.78,
                90.63,
                90.79,
                91.04
            ]
        },
        "USDSAR": {
            "price": 3.75,
            "prev_price": 3.75,
            "daily_chg": 0.02,
            "change_percent": 0.05,
            "trend": "UP",
            "sparkline": [
                3.75,
                3.75,
                3.74,
                3.75,
                3.75,
                3.75,
                3.75,
                3.75,
                3.75,
                3.75,
                3.75,
                3.75,
                3.74,
                3.75,
                3.75,
                3.75,
                3.75,
                3.75,
                3.75,
                3.75,
                3.75,
                3.75
            ]
        },
        "GOLD": {
            "price": 5059.3,
            "prev_price": 4975.9,
            "daily_chg": 1.68,
            "change_percent": 0.74,
            "trend": "UP",
            "sparkline": [
                4831.8,
                4908.8,
                4976.2,
                5079.7,
                5079.9,
                5301.6,
                5318.4,
                4713.9,
                4622.5,
                4903.7,
                4920.4,
                4861.4,
                4951.2,
                5050.9,
                5003.8,
                5071.6,
                4923.7,
                5022.0,
                4882.9,
                4986.5,
                4975.9,
                5059.3
            ]
        },
        "OIL": {
            "price": 66.39,
            "prev_price": 66.43,
            "daily_chg": -0.06,
            "change_percent": 5.57,
            "trend": "DOWN",
            "sparkline": [
                60.62,
                59.36,
                61.07,
                60.63,
                62.39,
                63.21,
                65.42,
                65.21,
                62.14,
                63.21,
                65.14,
                63.29,
                63.55,
                64.36,
                63.96,
                64.63,
                62.84,
                62.89,
                62.33,
                65.19,
                66.43,
                66.39
            ]
        },
        "COPPER": {
            "price": 5.83,
            "prev_price": 5.73,
            "daily_chg": 1.76,
            "change_percent": 0.66,
            "trend": "UP",
            "sparkline": [
                5.73,
                5.74,
                5.91,
                5.98,
                5.83,
                5.89,
                6.18,
                5.9,
                5.8,
                6.06,
                5.83,
                5.8,
                5.86,
                5.95,
                5.9,
                5.95,
                5.77,
                5.79,
                5.63,
                5.79,
                5.73,
                5.83
            ]
        },
        "NATGAS": {
            "price": 3.05,
            "prev_price": 3.0,
            "daily_chg": 1.7,
            "change_percent": -6.04,
            "trend": "UP",
            "sparkline": [
                4.88,
                5.05,
                5.28,
                6.8,
                6.95,
                7.46,
                3.92,
                4.35,
                3.24,
                3.31,
                3.46,
                3.51,
                3.42,
                3.14,
                3.12,
                3.16,
                3.22,
                3.24,
                3.03,
                3.01,
                3.0,
                3.05
            ]
        },
        "SILVER": {
            "price": 82.28,
            "prev_price": 77.57,
            "daily_chg": 6.08,
            "change_percent": 5.69,
            "trend": "UP",
            "sparkline": [
                92.21,
                95.98,
                100.93,
                115.08,
                105.52,
                113.11,
                114.04,
                78.29,
                76.78,
                83.04,
                84.17,
                76.53,
                76.74,
                82.07,
                80.22,
                83.75,
                75.55,
                77.85,
                73.45,
                77.51,
                77.57,
                82.28
            ]
        },
        "DAX": {
            "price": 25260.69,
            "prev_price": 25043.57,
            "daily_chg": 0.87,
            "change_percent": 1.85,
            "trend": "UP",
            "sparkline": [
                24856.47,
                24900.71,
                24933.08,
                24894.44,
                24822.79,
                24309.46,
                24538.81,
                24797.52,
                24780.79,
                24603.04,
                24491.06,
                24721.46,
                25014.87,
                24987.85,
                24856.15,
                24852.69,
                24914.88,
                24800.91,
                24998.4,
                25278.21,
                25043.57,
                25260.69
            ]
        },
        "CAC40": {
            "price": 8515.49,
            "prev_price": 8398.78,
            "daily_chg": 1.39,
            "change_percent": 2.39,
            "trend": "UP",
            "sparkline": [
                8148.89,
                8143.05,
                8131.15,
                8152.82,
                8066.68,
                8071.36,
                8126.53,
                8181.17,
                8179.5,
                8262.16,
                8238.17,
                8273.84,
                8323.28,
                8327.88,
                8313.24,
                8340.56,
                8311.74,
                8316.5,
                8361.46,
                8429.03,
                8398.78,
                8515.49
            ]
        },
        "STOXX600": {
            "price": 630.56,
            "prev_price": 625.33,
            "daily_chg": 0.84,
            "change_percent": 1.95,
            "trend": "UP",
            "sparkline": [
                608.86,
                608.34,
                609.57,
                613.11,
                608.51,
                607.14,
                611.0,
                617.31,
                617.93,
                618.12,
                611.65,
                617.12,
                621.41,
                620.97,
                621.58,
                618.52,
                617.7,
                618.52,
                621.29,
                628.69,
                625.33,
                630.56
            ]
        },
        "FTSE": {
            "price": 10686.9,
            "prev_price": 10627.0,
            "daily_chg": 0.56,
            "change_percent": 2.04,
            "trend": "UP",
            "sparkline": [
                10150.1,
                10143.4,
                10148.9,
                10207.8,
                10154.4,
                10171.8,
                10223.5,
                10341.6,
                10314.6,
                10402.3,
                10309.2,
                10369.8,
                10386.2,
                10353.8,
                10472.1,
                10402.4,
                10446.4,
                10473.7,
                10556.2,
                10686.2,
                10627.0,
                10686.9
            ]
        },
        "NIKKEI": {
            "price": 56825.7,
            "prev_price": 57467.83,
            "daily_chg": -1.12,
            "change_percent": 0.03,
            "trend": "DOWN",
            "sparkline": [
                52774.64,
                53688.89,
                53846.87,
                52885.25,
                53333.54,
                53358.71,
                53375.6,
                53322.85,
                52655.18,
                54720.66,
                54293.36,
                53818.04,
                54253.68,
                56363.94,
                57650.54,
                57639.84,
                56941.97,
                56806.41,
                56566.49,
                57143.84,
                57467.83,
                56825.7
            ]
        },
        "HANGSENG": {
            "price": 26413.35,
            "prev_price": 26705.94,
            "daily_chg": -1.1,
            "change_percent": -3.13,
            "trend": "DOWN",
            "sparkline": [
                26563.9,
                26487.51,
                26585.06,
                26629.96,
                26749.51,
                26765.52,
                27126.95,
                27826.91,
                27968.09,
                27387.11,
                26775.57,
                26834.77,
                26847.32,
                26885.24,
                26559.95,
                27027.16,
                27183.15,
                27266.38,
                27032.54,
                26567.12,
                26705.94,
                26413.35
            ]
        },
        "SHANGHAI": {
            "price": 4082.07,
            "prev_price": 4134.02,
            "daily_chg": -1.26,
            "change_percent": -0.99,
            "trend": "DOWN",
            "sparkline": [
                4112.6,
                4101.91,
                4114.0,
                4113.65,
                4116.94,
                4122.58,
                4136.16,
                4132.6,
                4139.9,
                4151.24,
                4157.98,
                4117.95,
                4015.75,
                4067.74,
                4102.2,
                4075.92,
                4065.58,
                4123.09,
                4128.37,
                4131.98,
                4134.02,
                4082.07
            ]
        },
        "SENSEX": {
            "price": 82814.71,
            "prev_price": 82498.14,
            "daily_chg": 0.38,
            "change_percent": -0.56,
            "trend": "UP",
            "sparkline": [
                81909.63,
                82307.37,
                81537.7,
                81857.48,
                82344.68,
                82566.37,
                82269.78,
                81666.46,
                83739.13,
                83817.69,
                83313.93,
                83580.4,
                84065.75,
                84273.92,
                84233.64,
                83674.92,
                82626.76,
                83277.15,
                83450.96,
                83734.25,
                82498.14,
                82814.71
            ]
        },
        "BOVESPA": {
            "price": 190534.0,
            "prev_price": 188534.0,
            "daily_chg": 1.06,
            "change_percent": 1.47,
            "trend": "UP",
            "sparkline": [
                166277.0,
                171817.0,
                175589.0,
                178859.0,
                178721.0,
                181919.0,
                184691.0,
                183134.0,
                181364.0,
                182793.0,
                185674.0,
                181708.0,
                182127.0,
                182950.0,
                186241.0,
                185929.0,
                189699.0,
                187766.0,
                186464.0,
                186016.0,
                188534.0,
                190534.0
            ]
        },
        "ASX200": {
            "price": 9081.4,
            "prev_price": 9086.2,
            "daily_chg": -0.05,
            "change_percent": 1.28,
            "trend": "DOWN",
            "sparkline": [
                8782.9,
                8848.7,
                8860.1,
                8941.6,
                8933.9,
                8966.1,
                8869.1,
                8778.6,
                8857.1,
                8927.8,
                8889.2,
                8708.8,
                8912.1,
                8867.4,
                9014.8,
                9043.5,
                8917.6,
                8966.8,
                8958.9,
                9007.0,
                9086.2,
                9081.4
            ]
        },
        "G_REIT": {
            "price": 27.06,
            "prev_price": 26.86,
            "daily_chg": 0.74,
            "change_percent": 0.3,
            "trend": "UP",
            "sparkline": [
                25.57,
                25.39,
                25.48,
                25.47,
                25.56,
                25.38,
                25.72,
                25.67,
                25.5,
                25.61,
                25.92,
                25.92,
                26.26,
                26.4,
                26.65,
                26.77,
                26.71,
                26.98,
                27.25,
                26.9,
                26.86,
                27.06
            ]
        },
        "US_HOUSING": {
            "price": 118.91,
            "prev_price": 117.85,
            "daily_chg": 0.9,
            "change_percent": -2.02,
            "trend": "UP",
            "sparkline": [
                114.84,
                113.6,
                111.69,
                111.4,
                110.08,
                109.64,
                110.41,
                108.4,
                109.11,
                111.57,
                115.35,
                115.31,
                117.27,
                117.05,
                120.35,
                120.6,
                119.11,
                121.36,
                120.14,
                119.59,
                117.85,
                118.91
            ]
        },
        "LOGISTICS": {
            "price": 40.83,
            "prev_price": 39.93,
            "daily_chg": 2.25,
            "change_percent": 1.96,
            "trend": "UP",
            "sparkline": [
                38.86,
                38.56,
                38.49,
                38.26,
                38.44,
                38.16,
                38.73,
                38.56,
                38.21,
                38.66,
                39.44,
                39.08,
                39.36,
                39.41,
                39.81,
                39.88,
                39.49,
                40.04,
                40.38,
                39.87,
                39.93,
                40.83
            ]
        },
        "INFRA": {
            "price": 68.56,
            "prev_price": 67.94,
            "daily_chg": 0.91,
            "change_percent": 0.31,
            "trend": "UP",
            "sparkline": [
                62.47,
                62.86,
                63.04,
                63.4,
                64.43,
                64.35,
                64.79,
                64.41,
                63.96,
                64.86,
                64.7,
                64.92,
                65.73,
                66.43,
                66.6,
                67.45,
                67.39,
                68.35,
                68.62,
                67.98,
                67.94,
                68.56
            ]
        },
        "HY_BOND": {
            "price": 81.0,
            "prev_price": 80.94,
            "daily_chg": 0.07,
            "change_percent": 0.19,
            "trend": "UP",
            "sparkline": [
                80.72,
                80.78,
                80.74,
                80.78,
                80.77,
                80.64,
                80.63,
                80.72,
                80.77,
                80.72,
                80.62,
                80.53,
                80.81,
                80.92,
                80.84,
                80.83,
                80.79,
                80.85,
                80.81,
                80.91,
                80.94,
                81.0
            ]
        },
        "IG_BOND": {
            "price": 111.59,
            "prev_price": 111.68,
            "daily_chg": -0.08,
            "change_percent": 0.0,
            "trend": "DOWN",
            "sparkline": [
                110.15,
                110.36,
                110.43,
                110.52,
                110.4,
                110.24,
                110.27,
                110.16,
                110.06,
                110.11,
                109.97,
                110.5,
                110.56,
                110.56,
                110.82,
                110.7,
                111.22,
                111.59,
                111.7,
                111.59,
                111.68,
                111.59
            ]
        },
        "TIPS": {
            "price": 111.19,
            "prev_price": 111.25,
            "daily_chg": -0.05,
            "change_percent": -0.18,
            "trend": "DOWN",
            "sparkline": [
                110.12,
                110.01,
                110.23,
                110.38,
                110.39,
                110.44,
                110.52,
                110.48,
                110.19,
                110.37,
                110.25,
                110.56,
                110.67,
                110.76,
                110.99,
                110.81,
                111.25,
                111.39,
                111.23,
                111.16,
                111.25,
                111.19
            ]
        },
        "SHY": {
            "price": 82.99,
            "prev_price": 82.98,
            "daily_chg": 0.01,
            "change_percent": -0.08,
            "trend": "UP",
            "sparkline": [
                82.59,
                82.56,
                82.59,
                82.62,
                82.64,
                82.64,
                82.67,
                82.74,
                82.7,
                82.69,
                82.73,
                82.86,
                82.86,
                82.88,
                82.93,
                82.85,
                82.93,
                83.06,
                83.03,
                82.98,
                82.98,
                82.99
            ]
        },
        "BALTIC": {
            "price": 11.73,
            "prev_price": 11.66,
            "daily_chg": 0.6,
            "change_percent": 2.09,
            "trend": "UP",
            "sparkline": [
                10.07,
                10.0,
                10.36,
                10.98,
                11.26,
                11.01,
                11.48,
                11.53,
                11.2,
                10.55,
                10.85,
                10.71,
                10.65,
                10.95,
                11.18,
                11.44,
                11.3,
                11.49,
                11.68,
                11.76,
                11.66,
                11.73
            ]
        },
        "SHIPPING": {
            "price": 40.15,
            "prev_price": 39.57,
            "daily_chg": 1.47,
            "change_percent": 6.19,
            "trend": "UP",
            "sparkline": [
                33.95,
                34.05,
                34.1,
                34.25,
                34.89,
                35.46,
                36.03,
                35.81,
                35.97,
                36.15,
                35.76,
                35.37,
                36.45,
                36.44,
                36.67,
                37.47,
                37.13,
                37.81,
                38.46,
                39.06,
                39.57,
                40.15
            ]
        },
        "AGRI": {
            "price": 26.03,
            "prev_price": 25.9,
            "daily_chg": 0.5,
            "change_percent": 0.93,
            "trend": "UP",
            "sparkline": [
                25.55,
                25.6,
                25.74,
                25.76,
                25.84,
                25.88,
                25.87,
                25.66,
                25.65,
                25.75,
                25.71,
                25.77,
                25.77,
                25.75,
                25.73,
                25.82,
                25.89,
                25.79,
                25.71,
                25.84,
                25.9,
                26.03
            ]
        },
        "SEMIS": {
            "price": 359.43,
            "prev_price": 355.84,
            "daily_chg": 1.01,
            "change_percent": 1.34,
            "trend": "UP",
            "sparkline": [
                348.14,
                348.67,
                344.71,
                343.07,
                351.08,
                360.46,
                361.13,
                346.3,
                352.69,
                345.64,
                330.38,
                330.83,
                348.51,
                352.77,
                351.43,
                360.2,
                351.5,
                354.66,
                354.1,
                357.92,
                355.84,
                359.43
            ]
        },
        "DEFENSE": {
            "price": 243.65,
            "prev_price": 243.49,
            "daily_chg": 0.07,
            "change_percent": 3.74,
            "trend": "UP",
            "sparkline": [
                240.27,
                235.82,
                235.07,
                233.38,
                237.02,
                233.69,
                232.78,
                232.38,
                231.16,
                234.49,
                228.0,
                226.18,
                233.93,
                234.84,
                233.21,
                230.95,
                232.53,
                234.87,
                238.17,
                240.32,
                243.49,
                243.65
            ]
        },
        "RARE_EARTH": {
            "price": 89.0,
            "prev_price": 90.09,
            "daily_chg": -1.21,
            "change_percent": -0.78,
            "trend": "DOWN",
            "sparkline": [
                92.84,
                95.58,
                98.46,
                96.91,
                97.61,
                97.52,
                93.53,
                85.63,
                84.81,
                90.2,
                87.06,
                81.66,
                86.63,
                88.74,
                88.74,
                91.92,
                87.2,
                89.7,
                88.99,
                91.45,
                90.09,
                89.0
            ]
        },
        "CYBER": {
            "price": 63.9,
            "prev_price": 65.91,
            "daily_chg": -3.05,
            "change_percent": -4.38,
            "trend": "DOWN",
            "sparkline": [
                70.07,
                70.65,
                70.81,
                72.09,
                72.03,
                71.51,
                69.56,
                69.06,
                69.59,
                67.09,
                66.53,
                64.95,
                67.13,
                68.34,
                68.83,
                67.62,
                65.1,
                66.83,
                65.54,
                65.93,
                65.91,
                63.9
            ]
        },
        "GBPUSD": {
            "price": 0.74,
            "prev_price": 0.74,
            "daily_chg": 0.26,
            "change_percent": 1.39,
            "trend": "UP",
            "sparkline": [
                0.75,
                0.74,
                0.73,
                0.73,
                0.72,
                0.72,
                0.72,
                0.73,
                0.73,
                0.73,
                0.73,
                0.74,
                0.73,
                0.73,
                0.73,
                0.73,
                0.73,
                0.73,
                0.73,
                0.74,
                0.74,
                0.74
            ]
        },
        "AUDUSD": {
            "price": 1.41,
            "prev_price": 1.42,
            "daily_chg": -0.42,
            "change_percent": -0.19,
            "trend": "DOWN",
            "sparkline": [
                1.46,
                1.45,
                1.45,
                1.43,
                1.42,
                1.42,
                1.44,
                1.44,
                1.42,
                1.43,
                1.45,
                1.42,
                1.41,
                1.41,
                1.4,
                1.41,
                1.41,
                1.41,
                1.41,
                1.42,
                1.42,
                1.41
            ]
        },
        "USDCAD": {
            "price": 1.37,
            "prev_price": 1.37,
            "daily_chg": -0.06,
            "change_percent": 0.31,
            "trend": "DOWN",
            "sparkline": [
                1.38,
                1.37,
                1.37,
                1.36,
                1.35,
                1.35,
                1.36,
                1.37,
                1.36,
                1.37,
                1.37,
                1.37,
                1.36,
                1.36,
                1.36,
                1.36,
                1.36,
                1.36,
                1.36,
                1.37,
                1.37,
                1.37
            ]
        },
        "USDCNY": {
            "price": 6.91,
            "prev_price": 6.91,
            "daily_chg": 0.0,
            "change_percent": 0.0,
            "trend": "UP",
            "sparkline": [
                6.96,
                6.97,
                6.97,
                6.95,
                6.95,
                6.95,
                6.95,
                6.95,
                6.95,
                6.94,
                6.94,
                6.94,
                6.94,
                6.92,
                6.91,
                6.91,
                6.9,
                6.91,
                6.91,
                6.91,
                6.91,
                6.91
            ]
        },
        "USDCHF": {
            "price": 0.78,
            "prev_price": 0.77,
            "daily_chg": 0.41,
            "change_percent": 0.93,
            "trend": "UP",
            "sparkline": [
                0.8,
                0.79,
                0.78,
                0.78,
                0.76,
                0.77,
                0.76,
                0.77,
                0.78,
                0.78,
                0.78,
                0.78,
                0.78,
                0.77,
                0.77,
                0.77,
                0.77,
                0.77,
                0.77,
                0.77,
                0.77,
                0.78
            ]
        },
        "MOVE": {
            "price": 64.27,
            "change_percent": -5.53,
            "trend": "NORMAL",
            "sparkline": [
                59.56,
                56.5,
                56.25,
                55.77,
                56.12,
                57.43,
                60.73,
                59.2,
                59.3,
                57.54,
                57.51,
                62.16,
                63.62,
                62.74,
                64.55,
                61.35,
                68.57,
                70.1,
                68.84,
                64.19,
                68.03,
                64.27
            ]
        },
        "BREADTH": {
            "price": -0.53,
            "change_percent": 0.0,
            "trend": "HEALTHY",
            "sparkline": [
                0.0,
                -0.39,
                -0.87,
                -1.15,
                -1.71,
                -2.03,
                -1.7,
                -1.62,
                -1.61,
                -1.02,
                0.34,
                0.71,
                0.67,
                0.25,
                0.88,
                1.08,
                1.3,
                2.27,
                1.94,
                1.96,
                2.01,
                1.76
            ]
        },
        "SPY_MOMENTUM": {
            "price": 0.53,
            "change_percent": 0,
            "trend": "BALANCED",
            "sparkline": [
                0,
                0,
                0,
                0,
                0,
                0,
                0,
                0,
                0,
                0,
                0,
                0,
                0,
                0,
                0,
                0,
                0,
                0,
                0,
                0,
                0,
                0,
                0,
                0,
                0,
                0,
                0,
                0,
                0,
                0
            ]
        },
        "COPPER_GOLD": {
            "price": 1.15,
            "change_percent": 0,
            "trend": "RISK-OFF",
            "sparkline": [
                1.15,
                1.15,
                1.15,
                1.15,
                1.15,
                1.15,
                1.15,
                1.15,
                1.15,
                1.15,
                1.15,
                1.15,
                1.15,
                1.15,
                1.15,
                1.15,
                1.15,
                1.15,
                1.15,
                1.15,
                1.15,
                1.15,
                1.15,
                1.15,
                1.15,
                1.15,
                1.15,
                1.15,
                1.15,
                1.15
            ]
        }
    },
    "events": [
        {
            "code": "retail_sales",
            "name": "USD Retail Sales (MoM)",
            "date": "2026-02-24",
            "day": "TUE",
            "time": "08:30 EST",
            "impact": "high"
        },
        {
            "code": "boj",
            "name": "JPY Bank of Japan Policy Meeting",
            "date": "2026-02-26",
            "day": "THU",
            "time": "12:00 JST",
            "impact": "high"
        },
        {
            "code": "powell",
            "name": "USD Fed Chair Powell Testifies",
            "date": "2026-03-01",
            "day": "SUN",
            "time": "10:00 EST",
            "impact": "high"
        },
        {
            "code": "ecb",
            "name": "EUR ECB Monetary Policy Press Conference",
            "date": "2026-03-03",
            "day": "TUE",
            "time": "14:45 CET",
            "impact": "high"
        },
        {
            "code": "nfp",
            "name": "USD Non-Farm Payrolls (NFP)",
            "date": "2026-03-06",
            "day": "FRI",
            "time": "08:30 EST",
            "impact": "high"
        }
    ],
    "analysis": {
        "title": "Global Market Outlook",
        "content": "Range-bound volatility amid tariff-induced risk. The GMS score of 54 dictates a regime of heightened caution as fiscal-monetary nexus stability faces geopolitical friction. Despite credit spread compression in core indices, the sharp appreciation in precious metals and silver's convexity signal a flight to hard assets. While net liquidity remains robust, the tariff-driven regime degradation in Asian equities necessitates a tactical pivot. Exposure must focus on domestic defensive alpha. [MARKET STATUS: DEFENSIVE]",
        "reports": {
            "JP": "GMS54[MARKET STATUS: DEFENSIVE]",
            "EN": "Range-bound volatility amid tariff-induced risk. The GMS score of 54 dictates a regime of heightened caution as fiscal-monetary nexus stability faces geopolitical friction. Despite credit spread compression in core indices, the sharp appreciation in precious metals and silver's convexity signal a flight to hard assets. While net liquidity remains robust, the tariff-driven regime degradation in Asian equities necessitates a tactical pivot. Exposure must focus on domestic defensive alpha. [MARKET STATUS: DEFENSIVE]",
            "CN": "GMS54[MARKET STATUS: DEFENSIVE]",
            "ES": "Volatilidad lateral ante riesgos arancelarios. El GMS de 54 dicta un rgimen de cautela extrema donde el nexo fiscal-monetario enfrenta friccin geopoltica. La apreciacin de metales preciosos y la convexidad de la plata sealan una cobertura contra la degradacin del rgimen fiduciario. A pesar de la liquidez neta robusta, la contraccin en los ndices asiticos refleja un riesgo de cola por proteccionismo. Es imperativo priorizar activos defensivos hasta que el vector inflacionario se estabilice. [MARKET STATUS: DEFENSIVE]",
            "HI": "-       54  GMS         -  -                              ,        -                     [MARKET STATUS: DEFENSIVE]",
            "ID": "Volatilitas rentang terbatas di tengah risiko tarif. Skor GMS 54 menuntut kewaspadaan tinggi karena stabilitas fiskal-moneter menghadapi gesekan geopolitik yang signifikan. Apresiasi tajam pada logam mulia dan konveksitas perak menunjukkan lindung nilai terhadap degradasi rezim fiat. Meskipun likuiditas bersih tetap kokoh, kontraksi pada ekuitas Asia mencerminkan risiko ekor akibat proteksionisme. Fokus pada alfa defensif domestik sangat krusial hingga vektor inflasi mencapai ekuilibrium. [MARKET STATUS: DEFENSIVE]",
            "AR": "      .   GMS  54           .              .              .            . [MARKET STATUS: DEFENSIVE]",
            "DE": "Seitwrtsvolatilitt und fiskalisch-monetre Friktion. Der GMS-Score von 54 signalisiert ein neutrales Regime mit ausgeprgter Abwrtsneigung durch protektionistische Impulse. Whrend die Nettoliquiditt stabil bleibt, deutet die Konvexitt bei Edelmetallen auf eine Absicherung gegen Regime-Degradation hin. Die Abwertung asiatischer Equities infolge der Tarifankndigungen erfordert eine taktische Reallokation in defensive Sektoren. Eine Akkumulation ist erst nach einer Stabilisierung indiziert. [MARKET STATUS: DEFENSIVE]",
            "FR": "Volatilit latrale et dgradation du rgime tarifaire. Le score GMS de 54 impose une prudence tactique alors que le nexus fiscal-montaire subit des frictions gopolitiques majeures. L'apprciation fulgurante des mtaux prcieux et la convexit de l'argent signalent une fuite vers les actifs tangibles face aux risques de dvaluation. Malgr une liquidit nette robuste, la contraction des marchs asiatiques souligne un risque de queue systmique. Une posture dfensive s'impose. [MARKET STATUS: DEFENSIVE]"
        }
    },
    "history_chart": [
        {
            "date": "2026-02-19T06:41:35Z",
            "score": 51
        },
        {
            "date": "2026-02-19T06:44:58Z",
            "score": 51
        },
        {
            "date": "2026-02-19T07:29:47Z",
            "score": 51
        },
        {
            "date": "2026-02-19T07:37:43Z",
            "score": 51
        },
        {
            "date": "2026-02-19T07:55:09Z",
            "score": 51
        },
        {
            "date": "2026-02-19T07:57:34Z",
            "score": 51
        },
        {
            "date": "2026-02-19T09:03:22Z",
            "score": 52
        },
        {
            "date": "2026-02-19T09:33:37Z",
            "score": 52
        },
        {
            "date": "2026-02-19T10:04:28Z",
            "score": 50
        },
        {
            "date": "2026-02-19T11:05:11Z",
            "score": 50
        },
        {
            "date": "2026-02-19T11:53:13Z",
            "score": 50
        },
        {
            "date": "2026-02-19T13:42:40Z",
            "score": 50
        },
        {
            "date": "2026-02-19T15:04:54Z",
            "score": 52
        },
        {
            "date": "2026-02-19T16:02:35Z",
            "score": 52
        },
        {
            "date": "2026-02-19T17:11:50Z",
            "score": 52
        },
        {
            "date": "2026-02-19T18:33:49Z",
            "score": 52
        },
        {
            "date": "2026-02-19T19:30:29Z",
            "score": 52
        },
        {
            "date": "2026-02-19T20:04:25Z",
            "score": 50
        },
        {
            "date": "2026-02-19T20:50:19Z",
            "score": 52
        },
        {
            "date": "2026-02-19T21:49:29Z",
            "score": 52
        },
        {
            "date": "2026-02-19T22:51:00Z",
            "score": 52
        },
        {
            "date": "2026-02-19T23:45:07Z",
            "score": 52
        },
        {
            "date": "2026-02-20T00:35:35Z",
            "score": 52
        },
        {
            "date": "2026-02-20T00:38:14Z",
            "score": 52
        },
        {
            "date": "2026-02-20T00:40:54Z",
            "score": 52
        },
        {
            "date": "2026-02-20T00:43:33Z",
            "score": 52
        },
        {
            "date": "2026-02-20T00:46:05Z",
            "score": 52
        },
        {
            "date": "2026-02-20T00:48:49Z",
            "score": 52
        },
        {
            "date": "2026-02-20T00:51:37Z",
            "score": 52
        },
        {
            "date": "2026-02-20T00:54:05Z",
            "score": 52
        },
        {
            "date": "2026-02-20T00:56:50Z",
            "score": 52
        },
        {
            "date": "2026-02-20T02:55:02Z",
            "score": 52
        },
        {
            "date": "2026-02-20T04:58:22Z",
            "score": 52
        },
        {
            "date": "2026-02-20T06:08:23Z",
            "score": 52
        },
        {
            "date": "2026-02-20T07:16:05Z",
            "score": 52
        },
        {
            "date": "2026-02-20T08:08:30Z",
            "score": 52
        },
        {
            "date": "2026-02-20T09:00:53Z",
            "score": 52
        },
        {
            "date": "2026-02-20T09:57:34Z",
            "score": 52
        },
        {
            "date": "2026-02-20T10:57:16Z",
            "score": 52
        },
        {
            "date": "2026-02-20T11:45:33Z",
            "score": 52
        },
        {
            "date": "2026-02-20T13:24:34Z",
            "score": 52
        },
        {
            "date": "2026-02-20T14:25:49Z",
            "score": 49
        },
        {
            "date": "2026-02-20T15:25:09Z",
            "score": 51
        },
        {
            "date": "2026-02-20T16:08:00Z",
            "score": 52
        },
        {
            "date": "2026-02-20T17:00:52Z",
            "score": 52
        },
        {
            "date": "2026-02-20T17:54:45Z",
            "score": 51
        },
        {
            "date": "2026-02-20T19:05:20Z",
            "score": 52
        },
        {
            "date": "2026-02-20T19:47:45Z",
            "score": 52
        },
        {
            "date": "2026-02-20T20:49:06Z",
            "score": 52
        },
        {
            "date": "2026-02-20T21:39:24Z",
            "score": 52
        },
        {
            "date": "2026-02-20T22:47:02Z",
            "score": 52
        },
        {
            "date": "2026-02-20T23:42:05Z",
            "score": 52
        },
        {
            "date": "2026-02-21T02:48:02Z",
            "score": 52
        },
        {
            "date": "2026-02-21T05:12:25Z",
            "score": 52
        },
        {
            "date": "2026-02-21T08:48:39Z",
            "score": 53
        },
        {
            "date": "2026-02-21T09:38:49Z",
            "score": 53
        },
        {
            "date": "2026-02-21T09:48:56Z",
            "score": 53
        },
        {
            "date": "2026-02-21T11:01:22Z",
            "score": 53
        },
        {
            "date": "2026-02-21T11:15:23Z",
            "score": 54
        },
        {
            "date": "2026-02-21T11:23:24Z",
            "score": 54
        }
    ],
    "intelligence": {
        "news": [
            {
                "title": "Trump announces new 10% global tariff after raging over Supreme Court loss",
                "link": "https://www.cnbc.com/2026/02/20/trump-global-trade-tariff-supreme-court.html",
                "isoDate": "2026-02-21T01:31:14+00:00Z"
            },
            {
                "title": "Trump says he's considering limited military strike against Iran",
                "link": "https://www.cnbc.com/2026/02/20/trump-says-hes-considering-limited-military-strike-against-iran.html",
                "isoDate": "2026-02-20T19:56:58+00:00Z"
            },
            {
                "title": "Tech giants commit billions to Indian AI as New Delhi pushes for superpower status",
                "link": "https://www.cnbc.com/2026/02/21/india-ai-summit-tech-giants-billion-dollar-investments.html",
                "isoDate": "2026-02-21T07:30:35+00:00Z"
            },
            {
                "title": "OpenAI resets spending expectations, tells investors compute target is around $600 billion by 2030",
                "link": "https://www.cnbc.com/2026/02/20/openai-resets-spend-expectations-targets-around-600-billion-by-2030.html",
                "isoDate": "2026-02-20T22:35:29+00:00Z"
            },
            {
                "title": "The best trades after geopolitical shocks as possible Iran conflict looms",
                "link": "https://www.cnbc.com/2026/02/20/the-best-trades-after-geopolitical-shocks-as-new-iran-conflict-looms.html",
                "isoDate": "2026-02-20T21:24:11+00:00Z"
            },
            {
                "title": "Retail industry says Trump tariff reversal is a win, even as uncertainty remains",
                "link": "https://www.cnbc.com/2026/02/20/supreme-court-trump-tariff-decision-retail-industry-reacts.html",
                "isoDate": "2026-02-20T22:01:28+00:00Z"
            }
        ],
        "translations": {
            "JP": [
                "10%",
                "",
                "AI",
                "OpenAI20306000",
                "",
                ""
            ],
            "CN": [
                "10%",
                "",
                "",
                "OpenAI20306000",
                "",
                ""
            ],
            "ES": [
                "Trump anuncia nuevo arancel global del 10% tras enfurecerse por la prdida ante la Corte Suprema",
                "Trump dice que est considerando un ataque militar limitado contra Irn",
                "Gigantes tecnolgicos comprometen miles de millones en IA para India mientras Nueva Delhi impulsa el estatus de superpotencia",
                "OpenAI restablece las expectativas de gasto, dice a los inversores que el objetivo de cmputo ronda los 600 mil millones de dlares para 2030",
                "Las mejores operaciones tras shocks geopolticos ante el posible conflicto en Irn",
                "La industria minorista dice que la reversin del arancel de Trump es una victoria, a pesar de la incertidumbre persistente"
            ],
            "HI": [
                "            10%      ",
                "               ",
                "        ,    AI       ",
                "OpenAI         ,    2030     600   ",
                "      -     ",
                "                   "
            ],
            "ID": [
                "Trump mengumumkan tarif global baru 10% setelah mengamuk atas kekalahan di Mahkamah Agung",
                "Trump mengatakan dia sedang mempertimbangkan serangan militer terbatas terhadap Iran",
                "Raksasa teknologi berkomitmen miliaran untuk AI India saat New Delhi mendorong status negara adidaya",
                "OpenAI menetapkan kembali ekspektasi pengeluaran, memberi tahu investor target komputasi sekitar $600 miliar pada tahun 2030",
                "Perdagangan terbaik setelah guncangan geopolitik saat potensi konflik Iran membayangi",
                "Industri ritel mengatakan pembalikan tarif Trump adalah kemenangan, bahkan ketika ketidakpastian tetap ada"
            ],
            "AR": [
                "        10%       ",
                "        ",
                "                ",
                "OpenAI            600     2030",
                "         ",
                "               "
            ],
            "DE": [
                "Trump kndigt neue globale Zoll von 10 % an, nachdem er sich ber Supreme Court-Niederlage aufgeregt hat",
                "Trump sagt, er erwgt einen begrenzten Militrschlag gegen den Iran",
                "Tech-Giganten investieren Milliarden in indische KI, whrend Neu-Delhi auf Supermachtstatus drngt",
                "OpenAI setzt Ausgabenerwartungen zurck, teilt Investoren mit, dass das Rechenziel bis 2030 rund 600 Milliarden US-Dollar betrgt",
                "Die besten Trades nach geopolitischen Schocks bei mglichem Iran-Konflikt",
                "Einzelhandelsbranche bezeichnet Trump-Zollumkehr als Sieg, auch wenn Unsicherheit bleibt"
            ],
            "FR": [
                "Trump annonce de nouveaux droits de douane mondiaux de 10 % aprs s'tre dchan contre une perte  la Cour suprme",
                "Trump dclare qu'il envisage une frappe militaire limite contre l'Iran",
                "Les gants de la technologie s'engagent  investir des milliards dans l'IA indienne alors que New Delhi pousse pour un statut de superpuissance",
                "OpenAI rinitialise ses attentes en matire de dpenses, indique aux investisseurs que l'objectif de calcul est d'environ 600 milliards de dollars d'ici 2030",
                "Les meilleures transactions aprs les chocs gopolitiques face au possible conflit iranien",
                "L'industrie de la vente au dtail considre l'inversion des tarifs de Trump comme une victoire, mme si l'incertitude demeure"
            ]
        },
        "last_updated": "2026-02-21T11:23:24.656827+00:00Z"
    },
    "system_status": "OPERATIONAL"
}