{
    "slug": "cci-commodity-channel-index",
    "lang": "CN",
    "title": "CCI (商品通道指数)",
    "type": "indicator",
    "category": "Technical",
    "sections": {
        "summary": "‘周期性偏差’发现者。CCI 衡量当前价格水平相对于给定时间段内平均价格水平的情况。主要用于发现新趋势或极端情况。+100/-100 是关键水平。",
        "deep_dive": "唐纳德·兰伯特 (Donald Lambert) 为商品设计了 CCI，因为商品具有周期性。它是无界的（与 RSI 不同）。高读数意味着价格与平均水平相比异常高。升至 +100 以上意味着强劲的上升趋势正在开始。",
        "council_debate": "{\"geopolitics\": \"大宗商品对供应冲击（战争）反应剧烈。CCI 比 RSI 能更好地捕捉这些冲击，因为它没有上限。当石油 CCI 在战争期间达到 +300 时，它准确地反映了‘无限’的恐慌需求。\", \"macro\": \"通胀周期就是大宗商品周期。我们在 CRB 指数上使用月度 CCI 来确定我们是处于‘硬资产’体制还是‘纸面资产’体制。月线图上的 CCI > 0 意味着拥有实物资产。\", \"quant\": \"我们使用 CCI 进行‘动量突破’。大多数指标在超买时说卖出。当 CCI 突破 +100 时，它说买入。这是一个反直觉的信号，在强劲的动量市场中效果很好。\", \"technical\": \"寻找‘零线拒绝 (Zero Line Reject)’。在上升趋势中，价格回调，CCI 跌至 0 附近，然后反弹。这是完美的‘逢低买入’切入点。它证实趋势仍然存在。\", \"policy\": \"欧佩克的决定推动石油 CCI。当欧佩克减产时，石油 CCI 突破 +100。这是政策驱动的趋势信号。不要与欧佩克对抗，也不要与 CCI 突破对抗。\", \"tech\": \"比特币比股票更模仿大宗商品。CCI 在比特币周线图上效果非常好。周收盘价高于 +100 通常标志着 6 个月牛市的开始。\"}",
        "forecast_risks": "窄幅区间的拉锯战。CCI 非常敏感。在波涛汹涌的市场中，它会反复穿越 +100 和 -100，产生虚假的突破信号。必须用趋势线显着过滤。",
        "gms_conclusion": "对于大宗商品和加密货币，CCI 优于 RSI。它尊重狂热的无限潜力。"
    },
    "model": "Antigravity-GMS-v1",
    "generated_at": "2026-01-29T15:00:00+00:00"
}