{
    "slug": "know-what-own",
    "lang": "HI",
    "title": "जानें कि आपके पास क्या है, और जानें कि आप इसके मालिक क्यों हैं (Know What You Own)",
    "type": "maxim",
    "category": "Maxim",
    "sections": {
        "summary": "पीटर लिंच द्वारा लोकप्रिय यह मैक्सिम, दृढ़ विश्वास के महत्व पर जोर देता है। आप उधार के विचारों पर भरोसा नहीं कर सकते। जब बाजार दुर्घटनाग्रस्त हो जाता है, तो आपको यह जानने की आवश्यकता है कि आपके पास इसे रखने का आत्मविश्वास रखने के लिए स्टॉक का मालिक क्यों है। यदि आपने इसे केवल इसलिए खरीदा है क्योंकि किसी और ने आपको बताया है, तो आप नीचे बेचेंगे।",
        "deep_dive": "निवेश टिकर प्रतीक के बारे में नहीं है; यह व्यवसाय के बारे में है। 'यह जानना कि आप क्या हैं' का अर्थ है व्यवसाय मॉडल, बैलेंस शीट और प्रतिस्पर्धी लाभ को समझना। 'यह जानना कि आप इसके मालिक क्यों हैं' का अर्थ है एक स्पष्ट थीसिस (जैसे, 'मैं इसका मालिक हूं क्योंकि वे क्लाउड कंप्यूटिंग में बाजार में हिस्सेदारी हासिल कर रहे हैं')। यदि थीसिस टूट जाता है, तो आप बेचते हैं। यदि कीमत टूट जाती है, लेकिन थीसिस बरकरार है, तो आप और खरीदते हैं।",
        "council_debate": "{\"geopolitics\": \"रणनीतिक संपत्ति। राष्ट्रों को पता होना चाहिए कि वे क्या हैं (महत्वपूर्ण बुनियादी ढांचा)। यदि कोई विदेशी विरोधी आपके बंदरगाहों या पावर ग्रिड का मालिक है, तो आपने संप्रभुता खो दी है। 'जानना कि आप इसके क्यों मालिक हैं' का अर्थ है उनके आर्थिक मूल्य से परे परिसंपत्तियों के रणनीतिक मूल्य को समझना।\", \"macro\": \"मुद्रा भंडार। केंद्रीय बैंक रिजर्व (गोल्ड, यूएसडी, ईयूआर) रखते हैं। उन्हें यह जानने की जरूरत है कि क्यों। क्या वे ध्रुवीय निपटान के लिए या भू -राजनीतिक उत्तोलन के लिए USD धारण कर रहे हैं? 'क्यों' रणनीति निर्धारित करता है जब मुद्रा में उतार -चढ़ाव होता है।\", \"quant\": \"कारक जोखिम। क्वेंट के पास 'स्टॉक' नहीं है; उनके पास 'कारक' (मूल्य, गति, गुणवत्ता) के मालिक हैं। हमें अपने कारक जोखिम को जानने की जरूरत है। अगर हमें लगता है कि हमारे पास 'टेक' पोर्टफोलियो है, लेकिन यह वास्तव में सिर्फ एक 'उच्च बीटा' पोर्टफोलियो है, तो हम आश्चर्यचकित होंगे जब यह व्यापक बाजार के साथ दुर्घटनाग्रस्त हो जाएगा।\", \"technical\": \"सेटअप सत्यापन। हम सिर्फ एक 'चार्ट' का मालिक नहीं हैं; हम एक विशिष्ट सेटअप (जैसे, बुल फ्लैग ब्रेकआउट) के मालिक हैं। हम जानते हैं कि हम इसके मालिक क्यों हैं: क्योंकि कीमत समर्थन से ऊपर है। यदि मूल्य समर्थन से नीचे गिरता है, तो 'क्यों' चला गया है, और हम बेचते हैं।\", \"policy\": \"विनियामक moats। कभी -कभी 'क्यों' एक नियामक लाभ होता है। हम एक उपयोगिता कंपनी के मालिक हैं क्योंकि इसमें सरकार द्वारा दी गई एकाधिकार है। यदि नीति बदलती है (doregulation), तो 'क्यों' वाष्पित हो जाता है।\", \"tech\": \"टेक स्टैक। आपको यह जानने की जरूरत है कि आप वास्तव में किस तकनीक पर सट्टेबाजी कर रहे हैं। क्या आप हार्डवेयर (नेवीडिया) या सॉफ्टवेयर (Microsoft) पर दांव लगा रहे हैं? क्या आप प्रोटोकॉल (Ethereum) या एप्लिकेशन (uniswap) पर दांव लगा रहे हैं? परिशुद्धता मायने रखती है।\"}",
        "forecast_risks": "शैली बहाव। जोखिम यह भूल रहा है कि आपने इसे क्यों खरीदा। आपने एक 'विकास' खेलने के रूप में एक स्टॉक खरीदा, लेकिन विकास धीमा हो जाता है। आप इसे पकड़ते रहते हैं क्योंकि यह एक लाभांश का भुगतान करता है (अब यह एक 'मूल्य' नाटक है)। यह शैली बहाव है। यदि मूल थीसिस मर चुकी है, तो इसे बेच दें। हारने वाले को रखने को सही ठहराने के लिए एक नई थीसिस का आविष्कार न करें।\", \"gms_conclusion\": \"यदि आप यह नहीं बता सकते कि आप इसे दो मिनट में 10 साल के बच्चे को इसका मालिक क्यों हैं, तो इसके मालिक नहीं हैं।\""
    },
    "model": "Antigravity-GMS-v1",
    "generated_at": "2026-01-29T16:00:00+00:00"
}